{
    "image": {
        "filename": "0206030818(0026)(0070)0101.jpg",
        "filename_rgb": "0206030818(0026)(0070)0301.jpg"
    },
    "csv": {
        "filename_csv": "0206030818(0026)(0070)0101.csv",
        "temp_start": "A6",
        "delimiter": ";"
    },
    "metadata": {
        "date_created": "2021.12.09. 11:46",
        "type": "JPG",
        "width": 640,
        "height": 512,
        "aspect_ratio": "5:4",
        "region_name": "변전소",
        "facility_id": "06",
        "facility": "전자접촉기",
        "camera_height": "2m",
        "camera_angle": 53.27,
        "status": "normal",
        "emissivity": 0.95,
        "obj_distance": 1.0,
        "reflected_temp": 24.0,
        "atmospheric_temp": 24.0,
        "relative_humidity": 50.0
    },
    "annotations": [
        {
            "id": "JgKzv9roBxcH_ZAQcuMM5",
            "category": "bounding_box",
            "class": "전자접촉기",
            "attributes": {
                "status": "normal",
                "standard": "DC110V 4a4b"
            },
            "data": {
                "x": 106,
                "y": 78,
                "width": 56,
                "height": 137
            }
        },
        {
            "id": "I-K17SZIaA3hedarLiWCg",
            "category": "bounding_box",
            "class": "전자접촉기",
            "attributes": {
                "status": "normal",
                "standard": "DC110V 4a4b"
            },
            "data": {
                "x": 147,
                "y": 75,
                "width": 42,
                "height": 140
            }
        },
        {
            "id": "gpdtDcLwfRJeAJC0ldMF9",
            "category": "bounding_box",
            "class": "전자접촉기",
            "attributes": {
                "status": "normal",
                "standard": "DC110V 4a4b"
            },
            "data": {
                "x": 177,
                "y": 78,
                "width": 52,
                "height": 139
            }
        },
        {
            "id": "KAjz1HatX85wM_LvHr0Or",
            "category": "bounding_box",
            "class": "전자접촉기",
            "attributes": {
                "status": "normal",
                "standard": "DC110V 4a4b"
            },
            "data": {
                "x": 216,
                "y": 73,
                "width": 46,
                "height": 146
            }
        },
        {
            "id": "l2WMi09CUGsSOejvBOB5t",
            "category": "bounding_box",
            "class": "전자접촉기",
            "attributes": {
                "status": "normal",
                "standard": "DC110V 4a4b"
            },
            "data": {
                "x": 255,
                "y": 67,
                "width": 47,
                "height": 153
            }
        },
        {
            "id": "sPGRpUVKwhSFMQa_dDrla",
            "category": "bounding_box",
            "class": "전자접촉기",
            "attributes": {
                "status": "normal",
                "standard": "DC110V 4a4b"
            },
            "data": {
                "x": 288,
                "y": 67,
                "width": 54,
                "height": 153
            }
        },
        {
            "id": "2stchXpRm4M0QsrA2HHq1",
            "category": "bounding_box",
            "class": "전자접촉기",
            "attributes": {
                "status": "normal",
                "standard": "DC110V 4a4b"
            },
            "data": {
                "x": 327,
                "y": 66,
                "width": 63,
                "height": 155
            }
        },
        {
            "id": "ykiP_fAZ6qZzHcD7fcQuq",
            "category": "bounding_box",
            "class": "전자접촉기",
            "attributes": {
                "status": "normal",
                "standard": "DC110V 4a4b"
            },
            "data": {
                "x": 486,
                "y": 59,
                "width": 50,
                "height": 155
            }
        },
        {
            "id": "5y_GiApDMdAq7BU4jZWDH",
            "category": "bounding_box",
            "class": "전자접촉기",
            "attributes": {
                "status": "normal",
                "standard": "DC110V 4a4b"
            },
            "data": {
                "x": 533,
                "y": 55,
                "width": 58,
                "height": 153
            }
        }
    ]
}