{
    "image": {
        "filename": "0201011001(0156)(0313)0101.jpg",
        "filename_rgb": "0201011001(0156)(0313)0301.jpg"
    },
    "csv": {
        "filename_csv": "0201011001(0156)(0313)0101.csv",
        "temp_start": "A6",
        "delimiter": ";"
    },
    "metadata": {
        "date_created": "2021.12.09. 11:41",
        "type": "JPG",
        "width": 640,
        "height": 512,
        "aspect_ratio": "5:4",
        "region_name": "변전소",
        "facility_id": "01",
        "facility": "단로기(DS)",
        "camera_height": "2m",
        "camera_angle": 86.59,
        "status": "normal",
        "emissivity": 0.95,
        "obj_distance": 1.0,
        "reflected_temp": 26.0,
        "atmospheric_temp": 26.0,
        "relative_humidity": 23.0
    },
    "annotations": [
        {
            "id": "ozkU3N5XzfBI3qZIPFw8_",
            "category": "bounding_box",
            "class": "단로기(DS)",
            "attributes": {
                "status": "normal",
                "standard": "24kV,1200A, 4P"
            },
            "data": {
                "x": 70,
                "y": 240,
                "width": 50,
                "height": 145
            }
        },
        {
            "id": "CDDKM_S40kWyZC4V2mbMh",
            "category": "bounding_box",
            "class": "단로기(DS)",
            "attributes": {
                "status": "normal",
                "standard": "24kV,1200A, 4P"
            },
            "data": {
                "x": 190,
                "y": 234,
                "width": 29,
                "height": 145
            }
        },
        {
            "id": "wllEtei0DOnFBYHTkbmA8",
            "category": "bounding_box",
            "class": "단로기(DS)",
            "attributes": {
                "status": "normal",
                "standard": "24kV,1200A, 4P"
            },
            "data": {
                "x": 421,
                "y": 237,
                "width": 37,
                "height": 132
            }
        }
    ]
}