{
    "image": {
        "filename": "0207010907(1507)(0437)0101.jpg",
        "filename_rgb": "0207010907(1507)(0437)0301.jpg"
    },
    "csv": {
        "filename_csv": "0207010907(1507)(0437)0101.csv",
        "temp_start": "A6",
        "delimiter": ";"
    },
    "metadata": {
        "date_created": "2021.12.09. 11:48",
        "type": "JPG",
        "width": 640,
        "height": 512,
        "aspect_ratio": "5:4",
        "region_name": "변전소",
        "facility_id": "07",
        "facility": "케이블&부스 연결개소",
        "camera_height": "2m",
        "camera_angle": 106.12,
        "status": "normal",
        "emissivity": 0.95,
        "obj_distance": 1.0,
        "reflected_temp": 24.5,
        "atmospheric_temp": 24.5,
        "relative_humidity": 10.0
    },
    "annotations": [
        {
            "id": "wfuhPR2hpH9VoSItlzCNm",
            "category": "bounding_box",
            "class": "케이블&부스 연결개소",
            "attributes": {
                "status": "normal",
                "standard": "22.9KV"
            },
            "data": {
                "x": 393,
                "y": 133,
                "width": 70,
                "height": 377
            }
        },
        {
            "id": "KeEcUbT9THRsNaPxwQnNb",
            "category": "bounding_box",
            "class": "케이블&부스 연결개소",
            "attributes": {
                "status": "normal",
                "standard": "22.9KV"
            },
            "data": {
                "x": 283,
                "y": 136,
                "width": 51,
                "height": 373
            }
        },
        {
            "id": "FBOk3f3VvZjStoFRf5SSk",
            "category": "bounding_box",
            "class": "케이블&부스 연결개소",
            "attributes": {
                "status": "normal",
                "standard": "22.9KV"
            },
            "data": {
                "x": 153,
                "y": 136,
                "width": 48,
                "height": 374
            }
        }
    ]
}