{
    "image": {
        "filename": "0203030908(0142)(0517)0102.jpg",
        "filename_rgb": "0203030908(0142)(0517)0302.jpg"
    },
    "csv": {
        "filename_csv": "0203030908(0142)(0517)0102.csv",
        "temp_start": "A6",
        "delimiter": ";"
    },
    "metadata": {
        "date_created": "2021.12.09. 11:43",
        "type": "JPG",
        "width": 640,
        "height": 512,
        "aspect_ratio": "5:4",
        "region_name": "변전소",
        "facility_id": "03",
        "facility": "변압기 케이블 연결개소 포함",
        "camera_height": "2m",
        "camera_angle": 139.26,
        "status": "danger",
        "emissivity": 0.95,
        "obj_distance": 1.0,
        "reflected_temp": 24.5,
        "atmospheric_temp": 24.5,
        "relative_humidity": 10.0
    },
    "annotations": [
        {
            "id": "GKTNuJ_KTztuQdrrWiiXu",
            "category": "bounding_box",
            "class": "변압기 케이블 연결개소 포함",
            "attributes": {
                "status": "normal",
                "standard": "6.6KV,380/220V,150kVA"
            },
            "data": {
                "x": 85,
                "y": 163,
                "width": 114,
                "height": 291
            }
        },
        {
            "id": "HB6EVKLoEBe5XL4SWx2tC",
            "category": "bounding_box",
            "class": "변압기 케이블 연결개소 포함",
            "attributes": {
                "status": "normal",
                "standard": "6.6KV,380/220V,150kVA"
            },
            "data": {
                "x": 268,
                "y": 105,
                "width": 83,
                "height": 336
            }
        },
        {
            "id": "NWbaCKFaHCufGNAg54Ua_",
            "category": "bounding_box",
            "class": "변압기 케이블 연결개소 포함",
            "attributes": {
                "status": "normal",
                "standard": "6.6KV,380/220V,150kVA"
            },
            "data": {
                "x": 368,
                "y": 83,
                "width": 49,
                "height": 356
            }
        },
        {
            "id": "yg5apNCcGFBgTIbdM6StY",
            "category": "bounding_box",
            "class": "변압기 케이블 연결개소 포함",
            "attributes": {
                "status": "normal",
                "standard": "6.6KV,380/220V,150kVA"
            },
            "data": {
                "x": 436,
                "y": 52,
                "width": 60,
                "height": 201
            }
        }
    ]
}